utils/__init__.py
utils/bin2csv.py
utils/bin2csvgui.py
pybinlog-0.3.4.dist-info/LICENSE
pybinlog-0.3.4.dist-info/METADATA
pybinlog-0.3.4.dist-info/WHEEL
pybinlog-0.3.4.dist-info/entry_points.txt
pybinlog-0.3.4.dist-info/top_level.txt
pybinlog-0.3.4.dist-info/RECORD
