Metadata-Version: 2.1
Name: pybinlog
Version: 0.3.4
Summary: Utility functions to parse Ardupilot's log file in bin format. 
Home-page: https://github.com/tayyabkhalil-313/pybinlog
Author: Tayyab Khalil
Author-email: tayyabkhalilpm@gmail.com
License: MIT License
Download-URL: https://github.com/tayyabkhalil-313/pybinlog
Platform: UNKNOWN
License-File: LICENSE
Requires-Dist: PyQt5
Requires-Dist: pymavlink
